{
    "configurations": [
        {
            "name": "Mac",
            "browse": {
                "path": [
                    "${workspaceFolder}"
                ],
                "limitSymbolsToIncludedHeaders": true
            },
            "includePath": [
                "/Users/sandeepsharma/Academics/Eigen",
                "/opt/local/include/",
                "/opt/local/include/openmpi-mp/",
                "${workspaceFolder}",
                "/System/Library/Frameworks/Kernel.framework/Versions/A/Headers"
            ],
            "defines": [],
            "macFrameworkPath": [
                "/System/Library/Frameworks",
                "/Library/Frameworks"
            ],
            "compilerPath": "/usr/bin/clang",
            "cStandard": "c11",
            "cppStandard": "c++17",
            "intelliSenseMode": "clang-x64"
        }
    ],
    "version": 4
}